{
  "Поднятие уровня в одиночку": {
    "x": 369,
    "y": -1269
  },
  "Легендарный Лунный Скульптор": {
    "x": 448,
    "y": -1391
  },
  "Возвращение игрока": {
    "x": 218,
    "y": -1241
  },
  "Воин-скелет не смог защитить подземелье": {
    "x": 307,
    "y": -1054
  },
  "Всеведущий читатель": {
    "x": 220,
    "y": -1319
  },
  "Миром правят власть и деньги": {
    "x": 260,
    "y": -1381
  },
  "Мой папа слишком сильный": {
    "x": 331,
    "y": -1412
  },
  "BJ Алекс": {
    "x": 99,
    "y": 357
  },
  "Даже если ты меня не любишь": {
    "x": 245,
    "y": 301
  },
  "Если ты так сильно меня Ненавидишь": {
    "x": 266,
    "y": 352
  },
  "Такой же как ты": {
    "x": -22,
    "y": 186
  },
  "Сладкие деньки яойщиков": {
    "x": -60,
    "y": 262
  },
  "Мой подчинённый": {
    "x": 196,
    "y": 256
  },
  "Социальная температура": {
    "x": 257,
    "y": 403
  },
  "Математика": {
    "x": -720,
    "y": 1544
  },
  "Биологические факты": {
    "x": -614,
    "y": 1646
  },
  "Livers": {
    "x": -588,
    "y": 1480
  },
  "Химические fuckты": {
    "x": -788,
    "y": 1675
  },
  "Берсерк": {
    "x": -747,
    "y": 1400
  },
  "1000 признаков того, что ты не очень хороший шахматист (Новелла) / обучение шахматам": {
    "x": -866,
    "y": 1520
  },
  "Ты Здесь": {
    "x": -137,
    "y": 0
  },
  "В начале была ложь": {
    "x": -278,
    "y": -75
  },
  "Даос x Контракт с демоном": {
    "x": -74,
    "y": -155
  },
  "Ты будешь меня ненавидеть": {
    "x": -211,
    "y": -151
  },
  "18 Без Ограничения": {
    "x": -257,
    "y": -125
  },
  "Язык жестов": {
    "x": -399,
    "y": 4
  },
  "19 Дней - Однажды": {
    "x": 33,
    "y": 95
  },
  "Неприкасаемый": {
    "x": 195,
    "y": 132
  },
  "По кругу": {
    "x": 171,
    "y": -12
  },
  "Мегуми и Цугуми": {
    "x": -96,
    "y": 175
  },
  "Послезавтра": {
    "x": 117,
    "y": -17
  },
  "Никогда не пойму": {
    "x": 221,
    "y": 84
  },
  "Насыщенная жизнь": {
    "x": 128,
    "y": -64
  },
  "Прелести садизма: Другая история А": {
    "x": 237,
    "y": 1533
  },
  "Тайная жизнь знатной дамы": {
    "x": 138,
    "y": 1423
  },
  "Есть ли шанс": {
    "x": 134,
    "y": 1640
  },
  "Хрустящая любовь": {
    "x": 87,
    "y": 1529
  },
  "Мой секретарь - демон": {
    "x": 276,
    "y": 1675
  },
  "Горько-сладкий кон-панна": {
    "x": 278,
    "y": 1392
  },
  "Эта фарфоровая кукла влюбилась": {
    "x": 393,
    "y": 1535
  },
  "Убить Сталкера": {
    "x": 55,
    "y": 598
  },
  "Заговор войны в мире Мэри Сью": {
    "x": 171,
    "y": 731
  },
  "Моритат": {
    "x": 205,
    "y": 681
  },
  "Змеиный язык": {
    "x": -89,
    "y": 473
  },
  "До свидания, хозяин": {
    "x": 49,
    "y": 770
  },
  "История Нашей Жизни": {
    "x": 116,
    "y": 752
  },
  "Воспитание хозяина": {
    "x": -98,
    "y": 257
  },
  "Обаятельный  убийца Ллевеллин приглашает на ужин": {
    "x": 55,
    "y": 296
  },
  "Ю Су, это есть нельзя!": {
    "x": -43,
    "y": 438
  },
  "Расплата": {
    "x": -16,
    "y": 383
  },
  "Парень-Ракушка / Жемчужный Мальчик": {
    "x": -290,
    "y": 78
  },
  "Просьба уйти": {
    "x": 53,
    "y": 202
  },
  "Вишня цветет после зимы": {
    "x": -87,
    "y": 378
  },
  "Ноги, что не могут идти": {
    "x": -136,
    "y": 551
  },
  "Секрет работника К": {
    "x": -325,
    "y": 472
  },
  "Втрескайся в меня": {
    "x": 57,
    "y": 474
  },
  "Последний Рай": {
    "x": 30,
    "y": 518
  },
  "Тайные Отношения": {
    "x": -35,
    "y": 554
  },
  "Токийские мстители": {
    "x": 357,
    "y": -137
  },
  "Шухер! У нас новый студент!": {
    "x": 504,
    "y": -79
  },
  "Ветролом": {
    "x": 445,
    "y": -304
  },
  "Спаси меня": {
    "x": 511,
    "y": -149
  },
  "Слабейший Герой": {
    "x": 482,
    "y": -220
  },
  "Голубой период": {
    "x": 286,
    "y": -267
  },
  "Серафим конца": {
    "x": 397,
    "y": -267
  },
  "Под зелёным светом": {
    "x": -640,
    "y": 196
  },
  "Обмен": {
    "x": -799,
    "y": 214
  },
  "Вместе или порознь": {
    "x": -564,
    "y": 71
  },
  "Уроборос": {
    "x": -752,
    "y": 77
  },
  "Хьюго": {
    "x": -777,
    "y": 284
  },
  "Ночные этюды": {
    "x": -315,
    "y": 250
  },
  "Дорогой Бенджамин": {
    "x": -790,
    "y": 138
  },
  "Однажды я стала принцессой": {
    "x": -662,
    "y": -1063
  },
  "Тиран - Хорошая партия для злодейки": {
    "x": -791,
    "y": -973
  },
  "Перерождение тирана": {
    "x": -729,
    "y": -927
  },
  "Единственный исход злодейки — смерть": {
    "x": -782,
    "y": -1221
  },
  "Проснись, герой": {
    "x": -778,
    "y": -1141
  },
  "История об Императоре, повернувшем время вспять": {
    "x": -484,
    "y": -964
  },
  "Дочь великого мага": {
    "x": -812,
    "y": -1044
  },
  "Человек-бензопила": {
    "x": 655,
    "y": -25
  },
  "Человек-бензопила - История Химено, Аки и Табака.": {
    "x": 788,
    "y": -92
  },
  "Дорохедоро": {
    "x": 815,
    "y": -37
  },
  "Оглянись": {
    "x": 779,
    "y": 71
  },
  "Нападение петухов": {
    "x": 720,
    "y": 109
  },
  "Пэн Питер": {
    "x": 813,
    "y": 22
  },
  "Токийский Гуль": {
    "x": 423,
    "y": 3
  },
  "Любовь или ненависть": {
    "x": -133,
    "y": 52
  },
  "Легенда о русале": {
    "x": -454,
    "y": 28
  },
  "Перекрыть": {
    "x": -303,
    "y": -198
  },
  "Невеста титана": {
    "x": -373,
    "y": -60
  },
  "Любовь до упаду": {
    "x": -463,
    "y": 85
  },
  "Грабитель прудовых улиток": {
    "x": -151,
    "y": 99
  },
  "Начало после конца": {
    "x": 387,
    "y": -991
  },
  "Боевой Континент": {
    "x": 233,
    "y": -1025
  },
  "Прорыв игрока": {
    "x": 431,
    "y": -1133
  },
  "Перерождение в Аристократа со способностью анализа": {
    "x": 252,
    "y": -938
  },
  "Пик боевых искусств": {
    "x": 269,
    "y": -1106
  },
  "Игрок, который не может повысить уровень": {
    "x": 350,
    "y": -1140
  },
  "Слабейший учитель": {
    "x": 526,
    "y": -975
  },
  "Любовь — просто иллюзия": {
    "x": -261,
    "y": 184
  },
  "День до ночи": {
    "x": -407,
    "y": 288
  },
  "Наша семья": {
    "x": -434,
    "y": 205
  },
  "Шторм зверя": {
    "x": -381,
    "y": 81
  },
  "Кровные узы": {
    "x": -478,
    "y": 314
  },
  "Позволь мне тебя ненавидеть": {
    "x": -422,
    "y": 142
  },
  "Клинок, рассекающий демонов": {
    "x": 776,
    "y": -157
  },
  "Клинок, рассекающий демонов: Несколько лет спустя – предложение Танджиро": {
    "x": 870,
    "y": -285
  },
  "Наруто": {
    "x": 939,
    "y": -158
  },
  "Ведьма и рыцарь выживают": {
    "x": 922,
    "y": -227
  },
  "Класс убийц": {
    "x": 730,
    "y": -283
  },
  "Свин-Паук": {
    "x": 922,
    "y": -85
  },
  "Ранкер, который живет второй раз": {
    "x": 234,
    "y": -846
  },
  "Королевские легенды": {
    "x": 91,
    "y": -892
  },
  "Немёртвый бывший генерал-рыцарь": {
    "x": 379,
    "y": -724
  },
  "Злодей Наоборот": {
    "x": 134,
    "y": -965
  },
  "Когда я перевоплотился, я был маленькой рыбкой, но я могу стать драконом, так что я сделаю все возможное!": {
    "x": 372,
    "y": -863
  },
  "Укус лунного света": {
    "x": -80,
    "y": -357
  },
  "Дьяволу известно твоё имя": {
    "x": -95,
    "y": -511
  },
  "Как взрастить вампира": {
    "x": -4,
    "y": -482
  },
  "Любовь с первого взгляда": {
    "x": 62,
    "y": -274
  },
  "Между любовью и влечением": {
    "x": -168,
    "y": -487
  },
  "Последний вампир": {
    "x": 75,
    "y": -89
  },
  "Я стал графским ублюдком": {
    "x": -84,
    "y": -669
  },
  "Итог": {
    "x": 141,
    "y": 300
  },
  "ДэмОн": {
    "x": 407,
    "y": 394
  },
  "Зависимость": {
    "x": 318,
    "y": 300
  },
  "Солнечное затмение": {
    "x": 267,
    "y": 460
  },
  "Твой след": {
    "x": 145,
    "y": 460
  },
  "Снова старшеклассник": {
    "x": -129,
    "y": 405
  },
  "Ночь, которую ты должен запомнить": {
    "x": -32,
    "y": 319
  },
  "10 лет моей любви к тебе": {
    "x": -145,
    "y": 172
  },
  "Первая фальшивая любовь Чжоу Чэна": {
    "x": -262,
    "y": 35
  },
  "Мы снова найдём друг друга": {
    "x": -298,
    "y": 135
  },
  "10 лет моей любви": {
    "x": -25,
    "y": 78
  },
  "Обманутый Ха Кён Су": {
    "x": 0,
    "y": 139
  },
  "Дарованный": {
    "x": -260,
    "y": 271
  },
  "Нань Хао и Шан Фэн": {
    "x": 417,
    "y": 234
  },
  "Закон Бессонницы": {
    "x": 537,
    "y": 119
  },
  "Падение": {
    "x": 176,
    "y": 196
  },
  "Их история": {
    "x": 568,
    "y": 297
  },
  "Любовный совет от великого герцога из Ада": {
    "x": 517,
    "y": 344
  },
  "Тайная любовь": {
    "x": 572,
    "y": 178
  },
  "Волк и найдёныш": {
    "x": 580,
    "y": 238
  },
  "Последняя молекула дофамина": {
    "x": 456,
    "y": 547
  },
  "Осень длиною в жизнь": {
    "x": 573,
    "y": 392
  },
  "Не уходи после школы": {
    "x": 539,
    "y": 484
  },
  "Я слышу солнечные вспышки": {
    "x": 516,
    "y": 532
  },
  "АЛЁшенька": {
    "x": 579,
    "y": 450
  },
  "Белая кровь": {
    "x": 1298,
    "y": 1223
  },
  "Петля": {
    "x": 1193,
    "y": 1119
  },
  "Сладкие следы от укусов": {
    "x": 1154,
    "y": 1258
  },
  "Дворянство": {
    "x": 1255,
    "y": 1365
  },
  "Теперь мне есть кого любить": {
    "x": 1404,
    "y": 1327
  },
  "Шальные девчонки": {
    "x": 1442,
    "y": 1186
  },
  "Свеча смерти": {
    "x": 1342,
    "y": 1082
  },
  "Работа глубокой ночью": {
    "x": -401,
    "y": 639
  },
  "Врата Ада": {
    "x": -501,
    "y": 465
  },
  "Нулевая охота": {
    "x": -340,
    "y": 639
  },
  "Жажда": {
    "x": -477,
    "y": 549
  },
  "СЕКС-манга": {
    "x": -443,
    "y": 602
  },
  "Безумная комбинация": {
    "x": -176,
    "y": -180
  },
  "Любимый цирк": {
    "x": -287,
    "y": -286
  },
  "Хороший день для Ын Су": {
    "x": -73,
    "y": -302
  },
  "Последний Омегаверс": {
    "x": -241,
    "y": -325
  },
  "Моя любимая русалка": {
    "x": -185,
    "y": -18
  },
  "Опыт! Сцена ХХ": {
    "x": -144,
    "y": -334
  },
  "Пойдём гулять!": {
    "x": -195,
    "y": -353
  },
  "Пустоцвет": {
    "x": 1107,
    "y": -1075
  },
  "Клуб самоубийц": {
    "x": 1259,
    "y": -1037
  },
  "Кровавый след": {
    "x": 1111,
    "y": -1226
  },
  "Коллекция ужасов от Дзюндзи Ито": {
    "x": 1256,
    "y": -1121
  },
  "Я теперь Мари": {
    "x": 1212,
    "y": -964
  },
  "Убийственные метаморфозы": {
    "x": 1206,
    "y": -1193
  },
  "Распятие Шести": {
    "x": 925,
    "y": -1026
  },
  "Тихая птица": {
    "x": -637,
    "y": 276
  },
  "Эйфория": {
    "x": -646,
    "y": 335
  },
  "До десяти": {
    "x": -513,
    "y": 156
  },
  "Воспоминания": {
    "x": -623,
    "y": 389
  },
  "Сердце Вампира": {
    "x": -583,
    "y": 438
  },
  "Безнадёжный": {
    "x": 178,
    "y": 400
  },
  "Путь к Тебе": {
    "x": 342,
    "y": 477
  },
  "Яойщица в теле идеального семе": {
    "x": -14,
    "y": 498
  },
  "Незнакомец на берегу моря": {
    "x": 254,
    "y": 563
  },
  "Стопроцентная уборка": {
    "x": 304,
    "y": 527
  },
  "Дикий Яой": {
    "x": 345,
    "y": 409
  },
  "Вельзевул": {
    "x": 589,
    "y": -316
  },
  "Моя геройская академия": {
    "x": 584,
    "y": -216
  },
  "Не умереть": {
    "x": 463,
    "y": -435
  },
  "Лавлок великой войны": {
    "x": 554,
    "y": -411
  },
  "Как подтолкнуть этого альфу?": {
    "x": -220,
    "y": 57
  },
  "Невеста Альфы": {
    "x": -72,
    "y": 50
  },
  "Превращение водяного оленя": {
    "x": -80,
    "y": -7
  },
  "Незапланированная беременность": {
    "x": -206,
    "y": 182
  },
  "Мой папочка - король демонов": {
    "x": -364,
    "y": 271
  },
  "Я основал Клуб Бессмертия": {
    "x": 15,
    "y": -781
  },
  "Берегись этой чертовки!": {
    "x": -299,
    "y": -849
  },
  "Выжить в качестве горничной": {
    "x": -139,
    "y": -812
  },
  "Убить злодейку": {
    "x": -61,
    "y": -822
  },
  "Да здравствует король!": {
    "x": -205,
    "y": -757
  },
  "Цвет безмолвия": {
    "x": -574,
    "y": -37
  },
  "Время игр с Хак До": {
    "x": -551,
    "y": -89
  },
  "Любовный заговор": {
    "x": -577,
    "y": 15
  },
  "Безмолвные грёзы": {
    "x": -466,
    "y": -165
  },
  "Странное приветствие": {
    "x": -20,
    "y": -87
  },
  "Дурачьё (Переиздание)": {
    "x": -135,
    "y": -114
  },
  "Дурачьё": {
    "x": -199,
    "y": -85
  },
  "Тайный Союз": {
    "x": 1399,
    "y": 663
  },
  "Идеальный тип": {
    "x": 1542,
    "y": 702
  },
  "Очарованный ею убийца": {
    "x": 1365,
    "y": 519
  },
  "Истории яндере": {
    "x": 1435,
    "y": 806
  },
  "Она — парень-ягодка": {
    "x": 1290,
    "y": 764
  },
  "Пиксель жизни": {
    "x": 1256,
    "y": 627
  },
  "Сладкая жизнь": {
    "x": 1506,
    "y": 561
  },
  "Злодейка, перевернувшая песочные часы": {
    "x": -603,
    "y": -1503
  },
  "Блондинка-призывательница": {
    "x": -746,
    "y": -1404
  },
  "Леди-малышка": {
    "x": -518,
    "y": -1384
  },
  "Я стала дрянной дочерью герцога": {
    "x": -445,
    "y": -1548
  },
  "Тень Императрицы": {
    "x": -512,
    "y": -1621
  },
  "Дэйзи: Как стать невестой герцога": {
    "x": -599,
    "y": -1655
  },
  "Я хочу стать тобой, пускай и всего на день": {
    "x": -691,
    "y": -1620
  },
  "Виляя хвостом": {
    "x": -88,
    "y": 138
  },
  "Собачья любовь": {
    "x": -141,
    "y": 295
  },
  "Захлестнуло как цунами": {
    "x": -309,
    "y": -22
  },
  "THIRDS: Когда кончается ад": {
    "x": -233,
    "y": 108
  },
  "Токкеби тоже нужен лес": {
    "x": -658,
    "y": 515
  },
  "Кот в картонной коробке": {
    "x": -537,
    "y": 637
  },
  "Готовься, воин": {
    "x": -593,
    "y": 615
  },
  "Дьявольская Контрактница": {
    "x": -633,
    "y": 573
  },
  "Жиголо": {
    "x": -271,
    "y": 514
  },
  "Наш лидер - омежка!": {
    "x": -216,
    "y": 220
  },
  "Плод языка": {
    "x": -209,
    "y": 585
  },
  "Пожалуйста, не открывайте  клетку зверя по своему желанию": {
    "x": -279,
    "y": 443
  },
  "Чья-то BL манхва": {
    "x": -245,
    "y": 556
  },
  "Кровь мадам Жизель": {
    "x": -1316,
    "y": 1181
  },
  "Птичка ласкового Токкэби": {
    "x": -1443,
    "y": 1257
  },
  "Глупый пёс и егo гoспoжа": {
    "x": -1322,
    "y": 1033
  },
  "Могу ли я тебя укусить?": {
    "x": -1188,
    "y": 1107
  },
  "Стена из стекла": {
    "x": -1443,
    "y": 1105
  },
  "Демон": {
    "x": -1310,
    "y": 1329
  },
  "Оборотень": {
    "x": -1187,
    "y": 1255
  },
  "Исчезни": {
    "x": 697,
    "y": 247
  },
  "Будь моим злодеем": {
    "x": 861,
    "y": 246
  },
  "Мир BL против не-BL-парня": {
    "x": 469,
    "y": 163
  },
  "Радужный свитер": {
    "x": 841,
    "y": 181
  },
  "Сброс": {
    "x": 850,
    "y": 308
  },
  "Большие проблемы подростков": {
    "x": 814,
    "y": 362
  },
  "Сергей-НЕ гей.": {
    "x": 753,
    "y": 396
  },
  "Банк крови": {
    "x": 134,
    "y": 168
  },
  "Уродливый император": {
    "x": 288,
    "y": 104
  },
  "Бабочка, кусающая тигра": {
    "x": 297,
    "y": 167
  },
  "Любовный треугольник": {
    "x": 289,
    "y": 224
  },
  "Физическое воспитание": {
    "x": 35,
    "y": 356
  },
  "Капучино с маршмэллоу": {
    "x": 159,
    "y": 51
  },
  "#немой": {
    "x": 291,
    "y": -23
  },
  "С замиранием сердца": {
    "x": 213,
    "y": -106
  },
  "Украденные слёзы": {
    "x": 267,
    "y": -82
  },
  "Ненормальный роман": {
    "x": -248,
    "y": -999
  },
  "Вторая жизнь злодейки": {
    "x": -401,
    "y": -970
  },
  "Как прожить жизнь, будучи старшей сестрой тирана": {
    "x": -429,
    "y": -778
  },
  "Мой выбор - концовка Императора": {
    "x": -184,
    "y": -950
  },
  "Тайна ласкового герцога": {
    "x": -323,
    "y": -1008
  },
  "Борьба в прямом эфире": {
    "x": 351,
    "y": -325
  },
  "Девушка ударник": {
    "x": 325,
    "y": -476
  },
  "Сильнейший в истории ученик Кеничи": {
    "x": 394,
    "y": -465
  },
  "Отброс": {
    "x": 213,
    "y": -377
  },
  "Проход защиты": {
    "x": 259,
    "y": -443
  },
  "Создатель злодейки": {
    "x": -821,
    "y": -1361
  },
  "Я стала властвующей антагонисткой романа": {
    "x": -892,
    "y": -1110
  },
  "Читра": {
    "x": -933,
    "y": -1173
  },
  "Жертва Принцессы": {
    "x": -899,
    "y": -1317
  },
  "Злодейка, которую убили 108 раз, но она все вспомнила. Дева с рубином творит чудеса": {
    "x": -936,
    "y": -1247
  },
  "Игра вслепую": {
    "x": -209,
    "y": 331
  },
  "Ловушка": {
    "x": -186,
    "y": 528
  },
  "Сволочь": {
    "x": -355,
    "y": 413
  },
  "Девять Камней": {
    "x": -371,
    "y": 357
  },
  "Прелести садизма: Другая история Б": {
    "x": -112,
    "y": 695
  },
  "Тарас Шевченко: Неизвестная история": {
    "x": -190,
    "y": 852
  },
  "Не давайте неосторожных обещаний": {
    "x": -121,
    "y": 867
  },
  "Потерянный король": {
    "x": -375,
    "y": 213
  },
  "Истинное Образование": {
    "x": 1696,
    "y": 59
  },
  "Боксёр": {
    "x": 1786,
    "y": -59
  },
  "Неубиваемый": {
    "x": 1747,
    "y": 198
  },
  "Крутой учитель Онидзука": {
    "x": 1842,
    "y": 84
  },
  "Месть психопата": {
    "x": 1551,
    "y": 36
  },
  "Учебная группа": {
    "x": 1604,
    "y": 175
  },
  "Жестокость: Исповедь полицейского-убийцы": {
    "x": 1644,
    "y": -80
  },
  "Подчинись мне": {
    "x": -93,
    "y": 527
  },
  "На равных": {
    "x": -57,
    "y": 706
  },
  "Изнасилование": {
    "x": -179,
    "y": 679
  },
  "Ублюдок FFF-ранга": {
    "x": 482,
    "y": -865
  },
  "Оттомэн": {
    "x": 619,
    "y": -911
  },
  "Логин Мурим": {
    "x": 524,
    "y": -729
  },
  "Это реально герой?": {
    "x": 594,
    "y": -762
  },
  "Маг-целитель: новый старт ~ Высшее исцеление: чары моментальной смерти и кража умений": {
    "x": 628,
    "y": -829
  },
  "Опасный круглосуточный магазин": {
    "x": -377,
    "y": -271
  },
  "Когда убийца влюбляется": {
    "x": -540,
    "y": -293
  },
  "Денег нет!": {
    "x": -382,
    "y": -436
  },
  "Арена нечистой силы": {
    "x": -535,
    "y": -354
  },
  "Небесное вторжение": {
    "x": -500,
    "y": -397
  },
  "Приятель на одну ночь": {
    "x": -449,
    "y": -424
  },
  "О, мой ассистент!": {
    "x": -348,
    "y": 158
  },
  "А вы знаете о феях?": {
    "x": -27,
    "y": -23
  },
  "AVLE": {
    "x": -107,
    "y": -52
  },
  "Выживание некроманта": {
    "x": -2,
    "y": 18
  },
  "Неромантичный": {
    "x": -407,
    "y": -146
  },
  "Барашек Исака": {
    "x": -477,
    "y": -38
  },
  "Моё дорогое убийство": {
    "x": -360,
    "y": -175
  },
  "Взрыв": {
    "x": -449,
    "y": -93
  },
  "Будь моим питомцем": {
    "x": 57,
    "y": 426
  },
  "Партнер для БДСМ": {
    "x": 203,
    "y": 441
  },
  "Скучаю по тебе, Люцифер": {
    "x": 162,
    "y": 570
  },
  "И завтра ты тоже будешь рядом, Тодороки-кун": {
    "x": 115,
    "y": 590
  },
  "Хозяин хозяина": {
    "x": 190,
    "y": 523
  },
  "Владелица бусины": {
    "x": -452,
    "y": -272
  },
  "Когда якудза влюблён": {
    "x": -502,
    "y": -137
  },
  "Пентхаус XXX": {
    "x": -397,
    "y": -337
  },
  "Стигма": {
    "x": -322,
    "y": -364
  },
  "Великий из Бродячих псов": {
    "x": 647,
    "y": -365
  },
  "Святая Ночь": {
    "x": 700,
    "y": -331
  },
  "Скрытые Герои": {
    "x": 729,
    "y": -209
  },
  "Не издевайся, Нагаторо-сан": {
    "x": 548,
    "y": 1536
  },
  "Девочка, любящая оскорблять": {
    "x": 646,
    "y": 1423
  },
  "Кагуя хочет, чтобы ей признались: Гении - война любви и разума": {
    "x": 643,
    "y": 1651
  },
  "Колючая груша": {
    "x": 519,
    "y": 1391
  },
  "Гия-сан, которая хочет смутить, и Тадамичи, которого не смутить": {
    "x": 513,
    "y": 1679
  },
  "Узаки-чан хочет тусоваться!": {
    "x": 698,
    "y": 1536
  },
  "Брошенная императрица": {
    "x": -876,
    "y": -1520
  },
  "Ваше величество, пожалуйста, не убивайте меня снова": {
    "x": -1027,
    "y": -1541
  },
  "Люсия": {
    "x": -902,
    "y": -1670
  },
  "Второй раунд в высшем свете": {
    "x": -985,
    "y": -1626
  },
  "Добродетель злодейки": {
    "x": -808,
    "y": -1653
  },
  "Княгиня чудовищ и Принцесса по контракту": {
    "x": -1007,
    "y": -1445
  },
  "Охотник-суицидник SSS-уровня": {
    "x": 448,
    "y": -527
  },
  "Мой наставник - небесный демон": {
    "x": 341,
    "y": -631
  },
  "Я стал главным ублюдком в этой новелле": {
    "x": 463,
    "y": -667
  },
  "Поднятие уровня с помощью еды": {
    "x": 602,
    "y": -526
  },
  "Уровень 0": {
    "x": 577,
    "y": -606
  },
  "Прогулка по воде": {
    "x": -879,
    "y": 172
  },
  "Марсель": {
    "x": -1016,
    "y": 87
  },
  "Сентиментальное родео: актёр гей-порно влюбился в натурала": {
    "x": -957,
    "y": 35
  },
  "Люби меня и Ненавидь меня": {
    "x": -988,
    "y": 287
  },
  "Ливета": {
    "x": -1032,
    "y": 225
  },
  "Негодник": {
    "x": -1040,
    "y": 155
  },
  "Как защитить старшего брата главной героини": {
    "x": -303,
    "y": -1626
  },
  "Что, если я приручила своего брата слишком хорошо": {
    "x": -232,
    "y": -1759
  },
  "Злодейка 99 уровня ~Я могу быть Скрытым Боссом, но я не Король Демонов~": {
    "x": -172,
    "y": -1556
  },
  "Под дубом": {
    "x": -276,
    "y": -1481
  },
  "Закон выживания благородной леди": {
    "x": -161,
    "y": -1674
  },
  "Нулевая игра": {
    "x": -350,
    "y": -1768
  },
  "Сладкая западня": {
    "x": 81,
    "y": 137
  },
  "Свидание вслепую": {
    "x": 221,
    "y": 30
  },
  "Элисед": {
    "x": 1002,
    "y": -748
  },
  "Сумеречный Хоулер": {
    "x": 1161,
    "y": -737
  },
  "Башня Бога": {
    "x": 1139,
    "y": -665
  },
  "неОРДИНАРНЫЕ": {
    "x": 1085,
    "y": -613
  },
  "Папочка фидер": {
    "x": 1140,
    "y": -817
  },
  "Кабинет Хейма": {
    "x": 1003,
    "y": -594
  },
  "Прирожденный наёмник": {
    "x": 816,
    "y": -859
  },
  "Герой, жаждущий мести, уничтожит врагов Силой Тьмы": {
    "x": 723,
    "y": -958
  },
  "Ты думаешь, что сможешь сбежать после реинкарнации, Братик?": {
    "x": 865,
    "y": -901
  },
  "Волшебник из другого мира не произносит заклинаний": {
    "x": 871,
    "y": -972
  },
  "Убийца Гоблинов": {
    "x": 805,
    "y": -1101
  },
  "Мастер меча, живущий на крыше": {
    "x": 851,
    "y": -1050
  },
  "Второй брак императрицы": {
    "x": -477,
    "y": -847
  },
  "Бывшая девушка великого воителя": {
    "x": -599,
    "y": -751
  },
  "Лилиен Туринская": {
    "x": -631,
    "y": -833
  },
  "Я решила перестать делать вид, что не замечаю измен": {
    "x": -354,
    "y": -916
  },
  "Становление королевой": {
    "x": -597,
    "y": -936
  },
  "Слышно даже без микрофона": {
    "x": 88,
    "y": -468
  },
  "Секс-игрушки атакуют!": {
    "x": -18,
    "y": -578
  },
  "Грудь месяца": {
    "x": 214,
    "y": -546
  },
  "Апория": {
    "x": 42,
    "y": -617
  },
  "Грудь моего Кохая великолепна~": {
    "x": 168,
    "y": -601
  },
  "Разворот кувырком": {
    "x": 107,
    "y": -624
  },
  "Постыдное♡приложение": {
    "x": 58,
    "y": -39
  },
  "Комнаты напротив": {
    "x": 38,
    "y": 247
  },
  "Клиническое испытание": {
    "x": 119,
    "y": -199
  },
  "Окна напротив": {
    "x": -74,
    "y": -75
  },
  "Приложение": {
    "x": 170,
    "y": -167
  },
  "Зона любовных ограничений": {
    "x": 22,
    "y": 703
  },
  "Любовный сглаз": {
    "x": 25,
    "y": 880
  },
  "Ужин с боссом": {
    "x": 143,
    "y": 835
  },
  "Бессонные метания": {
    "x": -35,
    "y": 861
  },
  "Движение любви": {
    "x": 86,
    "y": 869
  },
  "Лягушачий принц": {
    "x": 350,
    "y": -34
  },
  "Любимчик": {
    "x": 365,
    "y": 29
  },
  "Как у меня появился парень во время игры?": {
    "x": 392,
    "y": 83
  },
  "Остерегайтесь демонов": {
    "x": 375,
    "y": 144
  },
  "Шампанское и розы": {
    "x": -279,
    "y": -514
  },
  "Мафия демонов": {
    "x": -403,
    "y": -615
  },
  "Артур": {
    "x": -436,
    "y": -553
  },
  "Роман в один конец": {
    "x": -340,
    "y": -656
  },
  "Ису из семьи Кан": {
    "x": -255,
    "y": -660
  },
  "Придурок! Кто разрешил меня трогать?!": {
    "x": -119,
    "y": -232
  },
  "Четвёртый Оямато Тацуюки": {
    "x": -47,
    "y": -236
  },
  "Невероятное Приключение ДжоДжо Часть 7: Стил-Болл-Ран": {
    "x": 8,
    "y": -220
  },
  "Клуб Яричин": {
    "x": 48,
    "y": -175
  },
  "Приватные занятия": {
    "x": 131,
    "y": 112
  },
  "Звезда и фанат": {
    "x": -158,
    "y": 228
  },
  "Реинкарнация врача": {
    "x": 558,
    "y": -1226
  },
  "Джин": {
    "x": 545,
    "y": -1376
  },
  "Доктор": {
    "x": 620,
    "y": -1372
  },
  "Легенда о Регрессии": {
    "x": 711,
    "y": -1269
  },
  "Настоящий Мужчина": {
    "x": 513,
    "y": -1092
  },
  "Злодейка Каруна стала младше": {
    "x": 678,
    "y": -1333
  },
  "Наемный солдат": {
    "x": 763,
    "y": -720
  },
  "Свободный выбор": {
    "x": 969,
    "y": -908
  },
  "Выше Всех Богов": {
    "x": 845,
    "y": -706
  },
  "Повелитель Гоблинов": {
    "x": 912,
    "y": -742
  },
  "Басня": {
    "x": 966,
    "y": -827
  },
  "Реинкарнация Военного": {
    "x": 615,
    "y": -1023
  },
  "Мир вещей": {
    "x": -274,
    "y": 386
  },
  "Чёрное зеркало": {
    "x": -412,
    "y": 486
  },
  "Взаперти": {
    "x": -172,
    "y": 476
  },
  "Сломленный": {
    "x": -441,
    "y": 414
  },
  "Кодекс молчания": {
    "x": -361,
    "y": 538
  },
  "Поцелуй невесту": {
    "x": -619,
    "y": -263
  },
  "Бывший Якудза стал писателем BL": {
    "x": -675,
    "y": -164
  },
  "Магазинчик 'Longtime Red'": {
    "x": -658,
    "y": -219
  },
  "Тише, ты разбудишь ребенка": {
    "x": -671,
    "y": -102
  },
  "Дарую тебе свою кровь": {
    "x": -712,
    "y": 442
  },
  "Королевский слуга": {
    "x": -858,
    "y": 524
  },
  "Мой маленький вампир": {
    "x": -818,
    "y": 572
  },
  "Мой сосед - вампир": {
    "x": -877,
    "y": 464
  },
  "Переливание": {
    "x": -865,
    "y": 396
  },
  "Игра в прятки": {
    "x": -758,
    "y": 601
  },
  "Магия Вернувшегося Должна Быть Особенной": {
    "x": 392,
    "y": -1472
  },
  "Пожиратель книг": {
    "x": 324,
    "y": -1612
  },
  "Демон на ужин!": {
    "x": 482,
    "y": -1601
  },
  "Обещание, расцветшее в орхидеях": {
    "x": 534,
    "y": -1535
  },
  "Точка Возврата": {
    "x": 406,
    "y": -1629
  },
  "Система жизни": {
    "x": 258,
    "y": -1547
  },
  "Это же просто сон?!": {
    "x": 69,
    "y": 49
  },
  "Убить Злодея": {
    "x": 757,
    "y": -1033
  },
  "Крушитель: Новые волны": {
    "x": 672,
    "y": -1165
  },
  "Лавка убийцы": {
    "x": 593,
    "y": -1164
  },
  "Выживание с нуля": {
    "x": 728,
    "y": -1126
  },
  "Между прочим, мы живем вместе": {
    "x": -103,
    "y": 607
  },
  "Хладнокровный зверь": {
    "x": -46,
    "y": 619
  },
  "Люблю-ненавижу": {
    "x": 7,
    "y": 607
  },
  "Стокгольмский синдром": {
    "x": -214,
    "y": 758
  },
  "Упустить": {
    "x": -276,
    "y": 751
  },
  "Призрачный киллер": {
    "x": -326,
    "y": 720
  },
  "Хороший учитель": {
    "x": -499,
    "y": 245
  },
  "Не Могу Оторвать от Тебя Взгляд": {
    "x": -532,
    "y": 199
  },
  "Магистр Дьявольского Культа": {
    "x": -26,
    "y": 1987
  },
  "Культиватор из Будущего": {
    "x": -173,
    "y": 1964
  },
  "Список Ланъя": {
    "x": 41,
    "y": 2119
  },
  "Хаски и его учитель белый кот - Додзинси": {
    "x": -91,
    "y": 1853
  },
  "Смутно": {
    "x": 122,
    "y": 2006
  },
  "Старейшина укажет путь": {
    "x": -118,
    "y": 2102
  },
  "Система «Спаси-Себя-Сам» для главного злодея": {
    "x": 68,
    "y": 1874
  },
  "Обещанный Неверленд": {
    "x": -1688,
    "y": 4
  },
  "Атака Титанов": {
    "x": -1614,
    "y": 132
  },
  "Тетрадь смерти": {
    "x": -1761,
    "y": -125
  },
  "Колыбель Сейо": {
    "x": -1835,
    "y": 12
  },
  "Человечество на закуску": {
    "x": -1541,
    "y": -6
  },
  "Человеческая ферма": {
    "x": -1621,
    "y": -129
  },
  "Прощай, Питер Пэн": {
    "x": -1753,
    "y": 138
  },
  "Поцелуй меня, лжец": {
    "x": -260,
    "y": 327
  },
  "Невероятное приключение ДжоДжо — Часть 6: Каменный океан (В цвете)": {
    "x": -232,
    "y": 469
  },
  "Серый кардинал": {
    "x": 356,
    "y": 609
  },
  "Меланхоличное утро": {
    "x": 365,
    "y": 773
  },
  "Детка, этот парень просто псих": {
    "x": 516,
    "y": 657
  },
  "Эннеада": {
    "x": 434,
    "y": 758
  },
  "Шпинель": {
    "x": 485,
    "y": 718
  }
}